accelbyte_py_sdk/token_validation/__init__.py
accelbyte_py_sdk/token_validation/_bloom_filter.py
accelbyte_py_sdk/token_validation/_cache_types.py
accelbyte_py_sdk/token_validation/_ctypes.py
accelbyte_py_sdk/token_validation/_utils.py
accelbyte_py_sdk/token_validation/_validation.py
accelbyte_py_sdk/token_validation/caching.py
accelbyte_py_sdk/token_validation/iam.py
accelbyte_py_sdk/token_validation/mock.py
accelbyte_py_sdk_feat_token_validation-0.5.0.dist-info/METADATA
accelbyte_py_sdk_feat_token_validation-0.5.0.dist-info/WHEEL
accelbyte_py_sdk_feat_token_validation-0.5.0.dist-info/top_level.txt
accelbyte_py_sdk_feat_token_validation-0.5.0.dist-info/RECORD
