Metadata-Version: 2.4
Name: accelbyte-py-sdk-feat-token-validation
Version: 0.5.0
Summary: AccelByte Python SDK - Feature - Token Validation
Requires-Python: >=3.9
Requires-Dist: bitarray
Requires-Dist: mmh3
Requires-Dist: PyJWT[crypto]
Requires-Dist: accelbyte-py-sdk-core
Requires-Dist: accelbyte-py-sdk-service-iam
Requires-Dist: accelbyte-py-sdk-service-basic
